.gitignore
.pre-commit-config.yaml
.pylintrc
.readthedocs.yml
CODE_OF_CONDUCT.md
LICENSE
README.rst
README.rst.license
pyproject.toml
requirements.txt
samourai_scratch.py
setup.py
.github/PULL_REQUEST_TEMPLATE/adafruit_circuitpython_pr.md
.github/workflows/build.yml
.github/workflows/failure-help-text.yml
.github/workflows/release.yml
LICENSES/CC-BY-4.0.txt
LICENSES/MIT.txt
LICENSES/Unlicense.txt
docs/api.rst
docs/api.rst.license
docs/conf.py
docs/examples.rst
docs/examples.rst.license
docs/index.rst
docs/index.rst.license
docs/_static/favicon.ico
docs/_static/favicon.ico.license
examples/scratch_simpletest.py
samourai_circuitpython_scratch.egg-info/PKG-INFO
samourai_circuitpython_scratch.egg-info/SOURCES.txt
samourai_circuitpython_scratch.egg-info/dependency_links.txt
samourai_circuitpython_scratch.egg-info/requires.txt
samourai_circuitpython_scratch.egg-info/top_level.txt