Metadata-Version: 2.1
Name: samourai-circuitpython-scratch
Version: 0.0.1b1
Summary: Example library for testing updates to cookiecutter
Home-page: https://github.com/lesamouraipourpre/Samourai_CircuitPython_Scratch.git
Author: James Carr
Author-email: 
License: MIT
Keywords: adafruit blinka circuitpython micropython scratch
Platform: UNKNOWN
Classifier: Development Status :: 3 - Alpha
Classifier: Intended Audience :: Developers
Classifier: Topic :: Software Development :: Libraries
Classifier: Topic :: System :: Hardware
Classifier: License :: OSI Approved :: MIT License
Classifier: Programming Language :: Python :: 3
Classifier: Programming Language :: Python :: 3.4
Classifier: Programming Language :: Python :: 3.5
